{
  "os_list": [
    {
      "name": "Home Assistant OS 13.1 (RPi 5)",
      "description": "Open source home automation that puts local control and privacy first.",
      "url": "https://github.com/tiyicn123/operating-system/releases/download/13.1/haos_rpi5-64-13.1.img.xz",
      "icon": "https://version.home-assistant.io/brand/logo.png",
      "extract_size": 2147483648,
      "extract_sha256": "1364ae34f6562280e099c98e5304ee9c9bd905eb2bc23656d3ef59daebedf4cf",
      "release_date": "2024-11-28",
      "image_download_size": 302197696,
      "image_download_sha256": "723719c8b90ea915a0fae4c97ed865f2c12dae8dfc00b10f8d1d963355e790c3",
      "website": "https://www.home-assistant.io",
      "devices": [
        "pi5-64bit"
      ]
    },
    {
      "name": "Home Assistant OS 13.1 (RPi 4/400)",
      "description": "Open source home automation that puts local control and privacy first.",
      "url": "https://github.com/tiyicn123/operating-system/releases/download/13.1/haos_rpi4-64-13.1.img.xz",
      "icon": "https://version.home-assistant.io/brand/logo.png",
      "extract_size": 2147483648,
      "extract_sha256": "6c869cab6054e8864ae357fd66be684e6d61a56e6f3c2fb884ed8431c1f1119d",
      "release_date": "2024-11-28",
      "image_download_size": 295427096,
      "image_download_sha256": "db683225a2f7814d1af76f32184ea9954128a6329bbc7a6ad6da4106e50e53e8",
      "website": "https://www.home-assistant.io",
      "devices": [
        "pi4-64bit"
      ]
    },
    {
      "name": "Home Assistant OS 13.1 (RPi 3)",
      "description": "Open source home automation that puts local control and privacy first.",
      "url": "https://github.com/tiyicn123/operating-system/releases/download/13.1/haos_rpi3-64-13.1.img.xz",
      "icon": "https://version.home-assistant.io/brand/logo.png",
      "extract_size": 2147483648,
      "extract_sha256": "fad4bdc05f6612861635ddfad8649259221407832db095a478eb414da4267241",
      "release_date": "2024-11-28",
      "image_download_size": 291250976,
      "image_download_sha256": "850c32d5cc08d718f71025c04467f7083d825ae697ba804424981207fed2a7bd",
      "website": "https://www.home-assistant.io",
      "devices": [
        "pi3-64bit"
      ]
    },
    {
      "name": "Home Assistant OS Installer for Yellow",
      "description": "Installer for Home Assistant Yellow Kit.",
      "url": "https://github.com/NabuCasa/yellow-buildroot/releases/download/yellow-installer-20231025/yellow-installer-20231025.img.xz",
      "icon": "https://version.home-assistant.io/rpi-imager-yellow-installer.png",
      "extract_size": 68157440,
      "extract_sha256": "7e83edc8360d6a32010b18fa3ecd6fa9a6700be5ed47c21129534581697170a5",
      "release_date": "2023-10-25",
      "image_download_size": 33371388,
      "image_download_sha256": "fa1c4fdd72d116527cf37a1d3b849c480c08fff373b4a6c8d0017dae7da3e3f2",
      "website": "https://yellow.home-assistant.io",
      "devices": [
        "pi4-64bit"
      ]
    }
  ]
}
